percato/__init__.py
percato/characterutil.py
percato/container.py
percato/conv2dete.py
percato/datacheck.py
percato/main.py
percato/params.py
percato/predict.py
percato/run.py
percato/textutils.py
percato-0.1.0.dist-info/LICENSE
percato-0.1.0.dist-info/METADATA
percato-0.1.0.dist-info/WHEEL
percato-0.1.0.dist-info/entry_points.txt
percato-0.1.0.dist-info/top_level.txt
percato-0.1.0.dist-info/RECORD
