Metadata-Version: 2.1
Name: percato
Version: 0.1.0
Summary: Farsi data generator and an OCR tool for Farsi using Detectron2
Home-page: http://pypi.org/project/percato
Author: Sadiq SheshKhan
Author-email: sadiqush@gmail.com
License: GPLv3
Keywords: percato,ocr,farsi,persian,dataset
Platform: UNKNOWN
Requires-Python: >= 3
Requires-Dist: pillow
Requires-Dist: opencv-python
Requires-Dist: imagecorruptions
Requires-Dist: imgaug
